darknet2any/__init__.py
darknet2any/_version.py
darknet2any/darknet2onnx.py
darknet2any/darknet2torch.py
darknet2any/darknet2visual.py
darknet2any/onnx2mxr.py
darknet2any/onnx2trt.py
darknet2any/predict_darknet.py
darknet2any/predict_mxr.py
darknet2any/predict_onnx.py
darknet2any/predict_tflite.py
darknet2any/predict_torch.py
darknet2any/predict_trt.py
darknet2any/tool/__init__.py
darknet2any/tool/camera.py
darknet2any/tool/coco_annotation.py
darknet2any/tool/config.py
darknet2any/tool/darknet2onnx.py
darknet2any/tool/darknet2pytorch.py
darknet2any/tool/onnx2tensorflow.py
darknet2any/tool/region_loss.py
darknet2any/tool/tensorrt_utils.py
darknet2any/tool/torch_utils.py
darknet2any/tool/utils.py
darknet2any/tool/utils_iou.py
darknet2any/tool/utils_iou_test.py
darknet2any/tool/yolo_layer.py
darknet2any-0.7.4.dist-info/licenses/LICENSE
darknet2any-0.7.4.dist-info/METADATA
darknet2any-0.7.4.dist-info/WHEEL
darknet2any-0.7.4.dist-info/entry_points.txt
darknet2any-0.7.4.dist-info/top_level.txt
darknet2any-0.7.4.dist-info/RECORD
