Metadata-Version: 2.4
Name: darknet2any
Version: 0.7.4
Summary: converts from darknet weights to tf, onnx, trt and other model formats
Author-email: James Edmondson <james@koshee.ai>
License-Expression: Apache-2.0
Project-URL: Homepage, https://github.com/jredmondson/darknet2any
Project-URL: Issues, https://github.com/jredmondson/darknet2any/issues
Classifier: Programming Language :: Python :: 3
Classifier: Operating System :: OS Independent
Classifier: Environment :: GPU :: NVIDIA CUDA :: 12 :: 12.0
Classifier: Intended Audience :: Developers
Classifier: Intended Audience :: Science/Research
Classifier: Natural Language :: English
Classifier: Programming Language :: Python :: 3 :: Only
Classifier: Programming Language :: Python :: Implementation
Classifier: Topic :: Scientific/Engineering :: Artificial Intelligence
Classifier: Topic :: Scientific/Engineering :: Image Processing
Classifier: Topic :: Utilities
Requires-Python: >=3.8
License-File: LICENSE
Requires-Dist: numpy
Requires-Dist: torch
Requires-Dist: matplotlib
Requires-Dist: tqdm
Requires-Dist: easydict
Requires-Dist: Pillow
Requires-Dist: opencv_python
Requires-Dist: pycocotools
Requires-Dist: simple_onnx_processing_tools; platform_system == "Linux"
Requires-Dist: onnx
Requires-Dist: onnxsim-prebuilt; platform_system == "Linux"
Requires-Dist: onnx-graphsurgeon; platform_system == "Linux"
Requires-Dist: tensorflow
Requires-Dist: onnx2tf
Requires-Dist: tf-keras
Requires-Dist: psutil
Requires-Dist: h5py
Requires-Dist: ml_dtypes
Provides-Extra: tensorrt
Requires-Dist: tensorrt_cu12; extra == "tensorrt"
Requires-Dist: pycuda; extra == "tensorrt"
Requires-Dist: onnxruntime-gpu; extra == "tensorrt"
Provides-Extra: rocm
Requires-Dist: onnxruntime-rocm; extra == "rocm"
Provides-Extra: cpu
Requires-Dist: onnxruntime; extra == "cpu"
Provides-Extra: vino
Requires-Dist: onnxruntime-openvino; extra == "vino"
Provides-Extra: litert
Requires-Dist: ai-edge-litert; extra == "litert"
Dynamic: license-file
